[
  {
    "name": "penguin",
    "hash_algorithm": "MD5",
    "hash_value": "6399cc480d494bf1fcd7d16c42b1c11b"
  },
  {
    "name": "Google web server",
    "hash_algorithm": "MD5",
    "hash_value": "09b565a51e14b721a323f0ba44b2982a"
  },
  {
    "name": "SocialText",
    "hash_algorithm": "MD5",
    "hash_value": "506190fc55ceaa132f1bc305ed8472ca"
  },
  {
    "name": "PHPwiki (1.3.14) / gforge (4.6.99+svn6496) - wiki",
    "hash_algorithm": "MD5",
    "hash_value": "2cc15cfae55e2bb2d85b57e5b5bc3371"
  },
  {
    "name": "XOOPS cms",
    "hash_algorithm": "MD5",
    "hash_value": "389a8816c5b87685de7d8d5fec96c85b"
  },
  {
    "name": "NetScreen WebUI or 3Com Router",
    "hash_algorithm": "MD5",
    "hash_value": "f1876a80546b3986dbb79bad727b0374"
  },
  {
    "name": "Netscape 4.1",
    "hash_algorithm": "MD5",
    "hash_value": "226ffc5e483b85ec261654fe255e60be"
  },
  {
    "name": "Netscape iPlanet 6.0",
    "hash_algorithm": "MD5",
    "hash_value": "b25dbe60830705d98ba3aaf0568c456a"
  },
  {
    "name": "Netscape 6.0 (AOL)",
    "hash_algorithm": "MD5",
    "hash_value": "41e2c893098b3ed9fc14b821a2e14e73"
  },
  {
    "name": "SunOne 6.1",
    "hash_algorithm": "MD5",
    "hash_value": "a28ebcac852795fe30d8e99a23d377c1"
  },
  {
    "name": "Apache on Redhat",
    "hash_algorithm": "MD5",
    "hash_value": "71e30c507ca3fa005e2d1322a5aa8fb2"
  },
  {
    "name": "Zero byte favicon",
    "hash_algorithm": "MD5",
    "hash_value": "d41d8cd98f00b204e9800998ecf8427e"
  },
  {
    "name": "Parallels Plesk",
    "hash_algorithm": "MD5",
    "hash_value": "dcea02a5797ce9e36f19b7590752563e"
  },
  {
    "name": "Yahoo!",
    "hash_algorithm": "MD5",
    "hash_value": "6f767458b952d4755a795af0e4e0aa17"
  },
  {
    "name": "DotNetNuke (http",
    "hash_algorithm": "MD5",
    "hash_value": "5b0e3b33aa166c88cee57f83de1d4e55"
  },
  {
    "name": "Lotus-Domino",
    "hash_algorithm": "MD5",
    "hash_value": "7dbe9acc2ab6e64d59fa67637b1239df"
  },
  {
    "name": "Wordpress",
    "hash_algorithm": "MD5",
    "hash_value": "fa54dbf2f61bd2e0188e47f5f578f736"
  },
  {
    "name": "Wordpress - obsolete version",
    "hash_algorithm": "MD5",
    "hash_value": "6cec5a9c106d45e458fc680f70df91b0"
  },
  {
    "name": "E-zekiel",
    "hash_algorithm": "MD5",
    "hash_value": "81ed5fa6453cf406d1d82233ba355b9a"
  },
  {
    "name": "3-byte invalid favicon",
    "hash_algorithm": "MD5",
    "hash_value": "ecaa88f7fa0bf610a5a26cf545dcd3aa"
  },
  {
    "name": "vBulletin forum",
    "hash_algorithm": "MD5",
    "hash_value": "c1201c47c81081c7f0930503cae7f71a"
  },
  {
    "name": "Powered by Reynolds Web Solutions (Car sales CMS)",
    "hash_algorithm": "MD5",
    "hash_value": "edaaef7bbd3072a3a0c3fb3b29900bcb"
  },
  {
    "name": "Apache on Red Hat/Fedora",
    "hash_algorithm": "MD5",
    "hash_value": "d99217782f41e71bcaa8e663e6302473"
  },
  {
    "name": "Arris Touchstone Device",
    "hash_algorithm": "MD5",
    "hash_value": "a8fe5b8ae2c445a33ac41b33ccc9a120"
  },
  {
    "name": "ST 605",
    "hash_algorithm": "MD5",
    "hash_value": "d16a0da12074dae41980a6918d33f031"
  },
  {
    "name": "SpeedTouch",
    "hash_algorithm": "MD5",
    "hash_value": "befcded36aec1e59ea624582fcb3225c"
  },
  {
    "name": "i3micro VRG",
    "hash_algorithm": "MD5",
    "hash_value": "e4a509e78afca846cd0e6c0672797de5"
  },
  {
    "name": "status.net",
    "hash_algorithm": "MD5",
    "hash_value": "3541a8ed03d7a4911679009961a82675"
  },
  {
    "name": "Etherpad",
    "hash_algorithm": "MD5",
    "hash_value": "fa2b274fab800af436ee688e97da4ac4"
  },
  {
    "name": "OpenXPKI",
    "hash_algorithm": "MD5",
    "hash_value": "83245b21512cc0a0e7a67c72c3a3f501"
  },
  {
    "name": "Gitweb",
    "hash_algorithm": "MD5",
    "hash_value": "85138f44d577b03dfc738d3f27e04992"
  },
  {
    "name": "SSLstrip",
    "hash_algorithm": "MD5",
    "hash_value": "70625a6e60529a85cc51ad7da2d5580d"
  },
  {
    "name": "aMule (2.2.2)",
    "hash_algorithm": "MD5",
    "hash_value": "99306a52c76e19e3c298a46616c5899c"
  },
  {
    "name": "Stephen Turner Analog (6.0)",
    "hash_algorithm": "MD5",
    "hash_value": "31c16dd034e6985b4ba929e251200580"
  },
  {
    "name": "Ant docs manual (1.7.1)",
    "hash_algorithm": "MD5",
    "hash_value": "2d4cca83cf14d1adae178ad013bdf65b"
  },
  {
    "name": "Ant docs (1.7.1) / libjakarta-poi-java (3.0.2)",
    "hash_algorithm": "MD5",
    "hash_value": "032ecc47c22a91e7f3f1d28a45d7f7bc"
  },
  {
    "name": "apache2 (2.2.9) docs-manual",
    "hash_algorithm": "MD5",
    "hash_value": "31aa07fe236ee504c890a61d1f7f0a97"
  },
  {
    "name": "xsp (1.9.1)",
    "hash_algorithm": "MD5",
    "hash_value": "c0c4e7c0ac4da24ab8fc842d7f96723c"
  },
  {
    "name": "autopsy (2.08)",
    "hash_algorithm": "MD5",
    "hash_value": "d6923071afcee9cebcebc785da40b226"
  },
  {
    "name": "axyl (2.6.0)",
    "hash_algorithm": "MD5",
    "hash_value": "7513f4cf4802f546518f26ab5cfa1cad"
  },
  {
    "name": "b2evolution (2.4.2)",
    "hash_algorithm": "MD5",
    "hash_value": "de68f0ad7b37001b8241bce3887593c7"
  },
  {
    "name": "bmpx (0.40.14)",
    "hash_algorithm": "MD5",
    "hash_value": "140e3eb3e173bfb8d15778a578a213aa"
  },
  {
    "name": "cacti (0.8.7b)",
    "hash_algorithm": "MD5",
    "hash_value": "4f12cccd3c42a4a478f067337fe92794"
  },
  {
    "name": "CakePHP (1.1.x)",
    "hash_algorithm": "MD5",
    "hash_value": "c0533ae5d0ed638ba3fb3485d8250a28"
  },
  {
    "name": "cakephp (1.2.x-1.3x)",
    "hash_algorithm": "MD5",
    "hash_value": "66b3119d379aee26ba668fef49188dd3"
  },
  {
    "name": "caudium (1.4.12)",
    "hash_algorithm": "MD5",
    "hash_value": "09f5ea65a2d31da8976b9b9fd2bf853c"
  },
  {
    "name": "cgiirc (0.5.9)",
    "hash_algorithm": "MD5",
    "hash_value": "f276b19aabcb4ae8cda4d22625c6735f"
  },
  {
    "name": "chora2 (2.0.2)",
    "hash_algorithm": "MD5",
    "hash_value": "a18421fbf34123c03fb8b3082e9d33c8"
  },
  {
    "name": "chronicle (2.9) theme-steve",
    "hash_algorithm": "MD5",
    "hash_value": "23426658f03969934b758b7eb9e8f602"
  },
  {
    "name": "chronicle (2.9) theme-blog.mail-scanning.com",
    "hash_algorithm": "MD5",
    "hash_value": "75069c2c6701b2be250c05ec494b1b31"
  },
  {
    "name": "cimg (1.2.0.1)",
    "hash_algorithm": "MD5",
    "hash_value": "27c3b07523efd6c318a201cac58008ba"
  },
  {
    "name": "webcit (7.37)",
    "hash_algorithm": "MD5",
    "hash_value": "ae59960e866e2730e99799ac034eacf7"
  },
  {
    "name": "couchdb (0.8.0-0.9.1)",
    "hash_algorithm": "MD5",
    "hash_value": "2ab2aae806e8393b70970b2eaace82e0"
  },
  {
    "name": "cream (0.41)",
    "hash_algorithm": "MD5",
    "hash_value": "ddd76f1cfe31499ce3db6702991cbc45"
  },
  {
    "name": "cups (1.3.9) - doc",
    "hash_algorithm": "MD5",
    "hash_value": "74120b5bbc7be340887466ff6cfe66c6"
  },
  {
    "name": "doc-iana-20080601",
    "hash_algorithm": "MD5",
    "hash_value": "abee a75cf3c1bac42bbd0e96803c72b9"
  },
  {
    "name": "dokuwiki (0.0.20080505)",
    "hash_algorithm": "MD5",
    "hash_value": "3ef81fad2a3deaeb19f02c9cf67ed8eb"
  },
  {
    "name": "Drupal CMS (5.10)",
    "hash_algorithm": "MD5",
    "hash_value": "e6a9dc66179d8c9f34288b16a02f987e"
  },
  {
    "name": "dtc (0.28.10)",
    "hash_algorithm": "MD5",
    "hash_value": "bba9f1c29f100d265865626541b20a50"
  },
  {
    "name": "ebug-http (0.31)",
    "hash_algorithm": "MD5",
    "hash_value": "171429057ae2d6ad68e2cd6dcfd4adc1"
  },
  {
    "name": "eGroupWare (1.0.0.009, 1.4.004-2) (/phpgwapi/templates/idots/images/favicon.ico)",
    "hash_algorithm": "MD5",
    "hash_value": "f6e9339e652b8655d4e26f3e947cf212"
  },
  {
    "name": "freevo (1.8.1)",
    "hash_algorithm": "MD5",
    "hash_value": "093551287f13e0ee3805fee23c6f0e12"
  },
  {
    "name": "gallery (1.5.8)",
    "hash_algorithm": "MD5",
    "hash_value": "56753c5386a70edba6190d49252f00bb"
  },
  {
    "name": "garlic-doc (1.6)",
    "hash_algorithm": "MD5",
    "hash_value": "54b299f2f1c8b56c8c495f2ded6e3e0b"
  },
  {
    "name": "gforge (4.6.99+svn6496) - webcalendar",
    "hash_algorithm": "MD5",
    "hash_value": "857281e82ea34abbb79b9b9c752e33d2"
  },
  {
    "name": "gforge (4.6.99+svn6496) - images",
    "hash_algorithm": "MD5",
    "hash_value": "27a097ec0dbffb7db436384635d50415"
  },
  {
    "name": "gforge (4.6.99+svn6496)",
    "hash_algorithm": "MD5",
    "hash_value": "0e14c2f52b93613b5d1527802523b23f"
  },
  {
    "name": "glpi (0.70.2)",
    "hash_algorithm": "MD5",
    "hash_value": "c9339a2ecde0980f40ba22c2d237b94b"
  },
  {
    "name": "gollem (1.0.3)",
    "hash_algorithm": "MD5",
    "hash_value": "db1e3fe4a9ba1be201e913f9a401d794"
  },
  {
    "name": "gonzui (1.2+cvs20070129)",
    "hash_algorithm": "MD5",
    "hash_value": "921042508f011ae477d5d91b2a90d03f"
  },
  {
    "name": "gosa (2.5.16.1)",
    "hash_algorithm": "MD5",
    "hash_value": "ecab73f909ddd28e482ababe810447c8"
  },
  {
    "name": "gramps (3.0.1)",
    "hash_algorithm": "MD5",
    "hash_value": "c16b0a5c9eb3bfd831349739d89704ec"
  },
  {
    "name": "gsoap (2.7.9l)",
    "hash_algorithm": "MD5",
    "hash_value": "63d5627fc659adfdd5b902ecafe9100f"
  },
  {
    "name": "hercules (3.05)",
    "hash_algorithm": "MD5",
    "hash_value": "462794b1165c44409861fcad7e185631"
  },
  {
    "name": "horde-sam (0.1+cvs20080316) - silver",
    "hash_algorithm": "MD5",
    "hash_value": "3995c585b76bd5aa67cb6385431d378a"
  },
  {
    "name": "horde-sam (0.1+cvs20080316) - graphics",
    "hash_algorithm": "MD5",
    "hash_value": "ee3d6a9227e27a5bc72db3184dab8303"
  },
  {
    "name": "horde (3.2.1) - graphics/tango",
    "hash_algorithm": "MD5",
    "hash_value": "7cc1a052c86cc3d487957f7092a6d8c3"
  },
  {
    "name": "hplip (2.8.7) - installer",
    "hash_algorithm": "MD5",
    "hash_value": "5e99522b02f6ecadbb3665202357d775"
  },
  {
    "name": "Hewlett-Packard HPLIP (2.8.7) - doc",
    "hash_algorithm": "MD5",
    "hash_value": "39308a30527336e59d1d166d48c7742c"
  },
  {
    "name": "hunchentoot (0.15.7)",
    "hash_algorithm": "MD5",
    "hash_value": "43d4aa56dc796067b442c95976a864fd"
  },
  {
    "name": "ikiwiki (2.56ubuntu1)",
    "hash_algorithm": "MD5",
    "hash_value": "32bf63ac2d3cfe82425ce8836c9ce87c"
  },
  {
    "name": "Horde IMP (4.1.4 - 4.1.6, also used in Horde Groupware Webmail 1.0.1))",
    "hash_algorithm": "MD5",
    "hash_value": "f567fd4927f9693a7a2d6cacf21b51b6"
  },
  {
    "name": "Horde Groupware Webmail 1.0.1 (Ingo Theme, 1.1.5)",
    "hash_algorithm": "MD5",
    "hash_value": "919e132a62ea07fce13881470ba70293"
  },
  {
    "name": "jetty (5.1.14)",
    "hash_algorithm": "MD5",
    "hash_value": "ed7d5c39c69262f4ba95418d4f909b10"
  },
  {
    "name": "k3d (0.6.7.0)",
    "hash_algorithm": "MD5",
    "hash_value": "6900fab05a50a99d284405f46e5bc7f6"
  },
  {
    "name": "kdelibs (3.5.10-4.1.4)",
    "hash_algorithm": "MD5",
    "hash_value": "24d1e355c00e79dc13b84d5455534fe7"
  },
  {
    "name": "kdenetwork (4.1.4)",
    "hash_algorithm": "MD5",
    "hash_value": "8ab2f1a55bcb0cac227828afd5927d39"
  },
  {
    "name": "kolab-webadmin (2.1.0-20070510)",
    "hash_algorithm": "MD5",
    "hash_value": "54667bea91124121e98da49e55244935"
  },
  {
    "name": "Horde Groupware Webmail 1.0.1 (Kronolith Theme, 2.1.8)",
    "hash_algorithm": "MD5",
    "hash_value": "a5b126cdeaa3081f77a22b3e43730942"
  },
  {
    "name": "ktorrent (3.1.2)",
    "hash_algorithm": "MD5",
    "hash_value": "d00d85c8fb3a11170c1280c454398d51"
  },
  {
    "name": "lastfmproxy (1.3b)",
    "hash_algorithm": "MD5",
    "hash_value": "fa21ab1b1e1b4c9516afbd63e91275a9"
  },
  {
    "name": "ldap-account-manager (2.3.0)",
    "hash_algorithm": "MD5",
    "hash_value": "663ee93a41000b8959d6145f0603f599"
  },
  {
    "name": "boost (1.34.1)",
    "hash_algorithm": "MD5",
    "hash_value": "ea84a69cb146a947fac2ac7af3946297"
  },
  {
    "name": "flac (1.2.1)",
    "hash_algorithm": "MD5",
    "hash_value": "eb3e307f44581916d9f1197df2fc9de3"
  },
  {
    "name": "libitpp (4.0.4)",
    "hash_algorithm": "MD5",
    "hash_value": "669bc10baf11b43391294aac3e1b8c52"
  },
  {
    "name": "lucene (2.3.2)",
    "hash_algorithm": "MD5",
    "hash_value": "b8fe2ec1fcc0477c0d0f00084d824071"
  },
  {
    "name": "ramaze-ruby (0.3.9.1)",
    "hash_algorithm": "MD5",
    "hash_value": "12225e325909cee70c31f5a7ab2ee194"
  },
  {
    "name": "ramaze-ruby (0.3.9.1) - dispatcher",
    "hash_algorithm": "MD5",
    "hash_value": "6be5ebd07e37d0b415ec83396a077312"
  },
  {
    "name": "libswarmcache-java (1.0RC2+cvs20071027)",
    "hash_algorithm": "MD5",
    "hash_value": "20e208bb83f3eeed7c1aa8a6d9d3229d"
  },
  {
    "name": "mahara (1.0.4)",
    "hash_algorithm": "MD5",
    "hash_value": "5f8b52715c08dfc7826dad181c71dec8"
  },
  {
    "name": "Mantis Bug Tracker (1.1.2, /bugs/images/favicon.ico)",
    "hash_algorithm": "MD5",
    "hash_value": "ebe293e1746858d2548bca99c43e4969"
  },
  {
    "name": "mathomatic (14.0.6)",
    "hash_algorithm": "MD5",
    "hash_value": "0d42576d625920bcd121261fc5a6230b"
  },
  {
    "name": "mediatomb (0.11.0)",
    "hash_algorithm": "MD5",
    "hash_value": "f972c37bf444fb1925a2c97812e2c1eb"
  },
  {
    "name": "Horde Groupware Webmail 1.0.1 (Mnemo Theme, 2.1.2)",
    "hash_algorithm": "MD5",
    "hash_value": "f5f2df7eec0d1c3c10b58960f3f8fb26"
  },
  {
    "name": "Moodle (1.8.2, 1.9.x, multiple default themes)",
    "hash_algorithm": "MD5",
    "hash_value": "933a83c6e9e47bd1e38424f3789d121d"
  },
  {
    "name": "Moodle (1.8.2, 1.9.x, Cornflower Theme, /theme/cornflower/favicon.ico)",
    "hash_algorithm": "MD5",
    "hash_value": "b6652d5d71f6f04a88a8443a8821510f"
  },
  {
    "name": "movabletype-opensource (4.2~rc4)",
    "hash_algorithm": "MD5",
    "hash_value": "06b60d90ccfb79c2574c7fdc3ac23f05"
  },
  {
    "name": "mythplugins (0.21.0+fixes18722)",
    "hash_algorithm": "MD5",
    "hash_value": "21d80d9730a56b26dc9d252ffabb2987"
  },
  {
    "name": "Horde Groupware Webmail 1.0.1 (Nag Theme, 2.1.4)",
    "hash_algorithm": "MD5",
    "hash_value": "81df3601d6dc13cbc6bd8212ef50dd29"
  },
  {
    "name": "nagios (3.0.2)",
    "hash_algorithm": "MD5",
    "hash_value": "1c4201c7da53d6c7e48251d3a9680449"
  },
  {
    "name": "nanoblogger (3.3)",
    "hash_algorithm": "MD5",
    "hash_value": "28015fcdf84ca0d7d382394a82396927"
  },
  {
    "name": "netmrg (0.20)",
    "hash_algorithm": "MD5",
    "hash_value": "868e7b460bba6fe29a37aa0ceff851ba"
  },
  {
    "name": "ntop (3.3)",
    "hash_algorithm": "MD5",
    "hash_value": "0b2481ebc335a2d70fcf0cba0b3ce0fc"
  },
  {
    "name": "nulog (2.0)",
    "hash_algorithm": "MD5",
    "hash_value": "c30bf7e6d4afe1f02969e0f523d7a251"
  },
  {
    "name": "ocsinventory-server (1.01)",
    "hash_algorithm": "MD5",
    "hash_value": "9a8035769d7a129b19feb275a33dc5b4"
  },
  {
    "name": "parrot (0.4.13) - docs",
    "hash_algorithm": "MD5",
    "hash_value": "75aeda7adbd012fa93c4ae80336b4f45"
  },
  {
    "name": "pathological (1.1.3)",
    "hash_algorithm": "MD5",
    "hash_value": "70777a39f5d1de6d3873ffb309df35dd"
  },
  {
    "name": "perl-doc-html (5.10.0)",
    "hash_algorithm": "MD5",
    "hash_value": "82d746eb54b78b5449fbd583fc046ab2"
  },
  {
    "name": "phpgroupware (0.9.16.012)",
    "hash_algorithm": "MD5",
    "hash_value": "90c244c893a963e3bb193d6043a347bd"
  },
  {
    "name": "phpldapadmin (1.1.0.5)",
    "hash_algorithm": "MD5",
    "hash_value": "4b30eec86e9910e663b5a9209e9593b6"
  },
  {
    "name": "phpmyadmin (2.11.8.1) - pmd",
    "hash_algorithm": "MD5",
    "hash_value": "02dd7453848213a7b5277556bcc46307"
  },
  {
    "name": "phpmyadmin (2.11.8.1)",
    "hash_algorithm": "MD5",
    "hash_value": "d037ef2f629a22ddadcf438e6be7a325"
  },
  {
    "name": "pootle (1.1.0)",
    "hash_algorithm": "MD5",
    "hash_value": "8190ead2eb45952151ab5065d0e56381"
  },
  {
    "name": "prewikka (0.9.14)",
    "hash_algorithm": "MD5",
    "hash_value": "ba84999dfc070065f37a082ab0e36017"
  },
  {
    "name": "python-cherrypy (2.3.0-3.0.2)",
    "hash_algorithm": "MD5",
    "hash_value": "0f45c2c79ebe90d6491ddb111e810a56"
  },
  {
    "name": "MoinMoin (1.7.1)",
    "hash_algorithm": "MD5",
    "hash_value": "e551b7017a9bd490fc5b76e833d689bf"
  },
  {
    "name": "myghty (1.1)",
    "hash_algorithm": "MD5",
    "hash_value": "275e2e37fc7be50c1f03661ef8b6ce4f"
  },
  {
    "name": "myghty (1.1) - zblog",
    "hash_algorithm": "MD5",
    "hash_value": "68b329da9893e34099c7d8ad5cb9c940"
  },
  {
    "name": "turbogears (1.0.4.4) - genshi/elixir",
    "hash_algorithm": "MD5",
    "hash_value": "5488c1c8bf5a2264b8d4c8541e2d5ccd"
  },
  {
    "name": "python-werkzeug (0.3.1) - docs",
    "hash_algorithm": "MD5",
    "hash_value": "6927da350550f29bc641138825dff36f"
  },
  {
    "name": "python-werkzeug (0.3.1) - cupoftee-examples",
    "hash_algorithm": "MD5",
    "hash_value": "e3f28aab904e9edfd015f64dc93d487d"
  },
  {
    "name": "quantlib-refman-html (0.9.0)",
    "hash_algorithm": "MD5",
    "hash_value": "69f8a727f01a7e9b90a258bc30aaae6a"
  },
  {
    "name": "quickplot (0.8.13)",
    "hash_algorithm": "MD5",
    "hash_value": "b01625f4aa4cd64a180e46ef78f34877"
  },
  {
    "name": "qwik (0.8.4.4ubuntu2)",
    "hash_algorithm": "MD5",
    "hash_value": "af83bba99d82ea47ca9dafc8341ec110"
  },
  {
    "name": "roundcube (0.1.1)",
    "hash_algorithm": "MD5",
    "hash_value": "e9469705a8ac323e403d74c11425a62b"
  },
  {
    "name": "selfhtml (8.1.1)",
    "hash_algorithm": "MD5",
    "hash_value": "7f57bbd0956976e797b4e8eebdc6d733"
  },
  {
    "name": "solr (1.2.0) - docs",
    "hash_algorithm": "MD5",
    "hash_value": "69acfcb2659952bc37c54108d52fca70"
  },
  {
    "name": "solr (1.2.0) - admin",
    "hash_algorithm": "MD5",
    "hash_value": "ffc05799dee87a4f8901c458f7291d73"
  },
  {
    "name": "sork-forwards-h3 (3.0.1)",
    "hash_algorithm": "MD5",
    "hash_value": "aa2253a32823c8a5cba8d479fecedd3a"
  },
  {
    "name": "sork-passwd-h3 (3.0)",
    "hash_algorithm": "MD5",
    "hash_value": "a2e38a3b0cdf875cd79017dcaf4f2b55"
  },
  {
    "name": "sork-vacation-h3 (3.0.1)",
    "hash_algorithm": "MD5",
    "hash_value": "cb740847c45ea3fbbd80308b9aa4530a"
  },
  {
    "name": "spe (0.8.4.h)",
    "hash_algorithm": "MD5",
    "hash_value": "7c7b66d305e9377fa1fce9f9a74464d9"
  },
  {
    "name": "sql-ledger (2.8.15)",
    "hash_algorithm": "MD5",
    "hash_value": "0e2503a23068aac350f16143d30a1273"
  },
  {
    "name": "tea (17.6.1)",
    "hash_algorithm": "MD5",
    "hash_value": "1fd3fafc1d461a3d19e91dbbba03d0aa"
  },
  {
    "name": "Apache Tomcat (5.5.26), Alfresco Community",
    "hash_algorithm": "MD5",
    "hash_value": "4644f2d45601037b8423d45e13194c93"
  },
  {
    "name": "torrentflux (2.4)",
    "hash_algorithm": "MD5",
    "hash_value": "1de863a5023e7e73f050a496e6b104ab"
  },
  {
    "name": "torrentflux (2.4) - themes/G4E/",
    "hash_algorithm": "MD5",
    "hash_value": "83dea3d5d8c6feddec84884522b61850"
  },
  {
    "name": "torrentflux (2.4) - themes/BlueFlux/",
    "hash_algorithm": "MD5",
    "hash_value": "d1bc9681dce4ad805c17bd1f0f5cee97"
  },
  {
    "name": "transmission (1.34)",
    "hash_algorithm": "MD5",
    "hash_value": "8d13927efb22bbe7237fa64e858bb523"
  },
  {
    "name": "tulip (3.0.0~B6)",
    "hash_algorithm": "MD5",
    "hash_value": "5b015106854dc7be448c14b64867dfa5"
  },
  {
    "name": "Horde Groupware Webmail 1.0.1 (Turba Theme, 2.1.7)",
    "hash_algorithm": "MD5",
    "hash_value": "ff260e80f5f9ca4b779fbd34087f13cf"
  },
  {
    "name": "twiki (4.1.2) - logos/favicon.ico",
    "hash_algorithm": "MD5",
    "hash_value": "e7fc436d0bf31500ced7a7143067c337"
  },
  {
    "name": "twiki (4.1.2) - webpreferences",
    "hash_algorithm": "MD5",
    "hash_value": "9789c9ab400ea0b9ca8fcbd9952133bd"
  },
  {
    "name": "vdr-plugin-live (0.2.0)",
    "hash_algorithm": "MD5",
    "hash_value": "2b52c1344164d29dd8fb758db16aadb6"
  },
  {
    "name": "vdradmin-am (3.6.1)",
    "hash_algorithm": "MD5",
    "hash_value": "237f837bbc33cd98a9f47b20b284e2ad"
  },
  {
    "name": "vlc (0.9.4)",
    "hash_algorithm": "MD5",
    "hash_value": "6f7e92fe7e6a62661ac2b41528a78fc6"
  },
  {
    "name": "webcheck (1.10.2.0)",
    "hash_algorithm": "MD5",
    "hash_value": "2507c0b0a60ecdc816ba45482affaedf"
  },
  {
    "name": "websvn (2.0)",
    "hash_algorithm": "MD5",
    "hash_value": "ef5169b040925a716359d131afbea033"
  },
  {
    "name": "witty (2.1.5)",
    "hash_algorithm": "MD5",
    "hash_value": "f6d0a100b6dbeb5899f0975a1203fd85"
  },
  {
    "name": "yaws (1.77)",
    "hash_algorithm": "MD5",
    "hash_value": "81feac35654318fb16d1a567b8b941e7"
  },
  {
    "name": "znc (0.058)",
    "hash_algorithm": "MD5",
    "hash_value": "33b04fb9f2ec918f5f14b41527e77f6d"
  },
  {
    "name": "znc (0.058, webadmin/skins/default)",
    "hash_algorithm": "MD5",
    "hash_value": "6434232d43f27ef5462ba5ba345e03df"
  },
  {
    "name": "zoneminder (1.23.3)",
    "hash_algorithm": "MD5",
    "hash_value": "e07c0775523271d629035dc8921dffc7"
  },
  {
    "name": "Plone CMS (3.1.1)",
    "hash_algorithm": "MD5",
    "hash_value": "4eb846f1286ab4e7a399c851d7d84cca"
  },
  {
    "name": "Nessus 4.x Scanner Web Client",
    "hash_algorithm": "MD5",
    "hash_value": "e298e00b2ff6340343ddf2fc6212010b"
  },
  {
    "name": "LANCOM Systems",
    "hash_algorithm": "MD5",
    "hash_value": "240c36cd118aa1ff59986066f21015d4"
  },
  {
    "name": "COMpact 5020 VoIP",
    "hash_algorithm": "MD5",
    "hash_value": "ceb25c12c147093dc93ac8b2c18bebff"
  },
  {
    "name": "RapidShare",
    "hash_algorithm": "MD5",
    "hash_value": "05656826682ab3147092991ef5de9ef3"
  },
  {
    "name": "Rapid7 (NeXpose)",
    "hash_algorithm": "MD5",
    "hash_value": "e19ffb2bc890f5bdca20f10bfddb288d"
  },
  {
    "name": "owasp.org",
    "hash_algorithm": "MD5",
    "hash_value": "1f8c0b08fb6b556a6587517a8d5f290b"
  },
  {
    "name": "Apache on Mac OS X",
    "hash_algorithm": "MD5",
    "hash_value": "73778a17b0d22ffbb7d6c445a7947b92"
  },
  {
    "name": "JBoss Server",
    "hash_algorithm": "MD5",
    "hash_value": "799f70b71314a7508326d1d2f68f7519"
  },
  {
    "name": "Serena Collage (4.6, servlet/images/collage_app.ico)",
    "hash_algorithm": "MD5",
    "hash_value": "bd0f7466d35e8ba6cedd9c27110c5c41"
  },
  {
    "name": "Aruba Network Devices (HTTP(S) login page)",
    "hash_algorithm": "MD5",
    "hash_value": "dc0816f371699823e1e03e0078622d75"
  }
]
